verbosemanager/__init__.py
verbosemanager/counter.py
verbosemanager/decorator.py
verbosemanager/manager.py
verbosemanager-1.3.0.dist-info/LICENSE
verbosemanager-1.3.0.dist-info/METADATA
verbosemanager-1.3.0.dist-info/WHEEL
verbosemanager-1.3.0.dist-info/top_level.txt
verbosemanager-1.3.0.dist-info/RECORD
