Metadata-Version: 2.1
Name: verbosemanager
Version: 1.3.0
Summary: A library for managing verbose output on complex processes
Home-page: https://github.com/alexhroom/verbosemanager
Author: Alex H. Room
Author-email: alex.room@btinternet.com
Project-URL: Bug Tracker, https://github.com/alexhroom/verbosemanager/issues
Classifier: Programming Language :: Python :: 3
Classifier: License :: OSI Approved :: MIT License
Classifier: Operating System :: OS Independent
Requires-Python: >=3.6
License-File: LICENSE
